{
  "type": "elementalsmithing:fusion",
  "fusing_craft_0": {"item": "elementalsmithing:steel_ingot"},
  "fusing_craft_1": {"item": "minecraft:fire_charge"},
  "fusing_craft_2": {"item": "elementalsmithing:steel_ingot"},
  "fusing_craft_3": {"item": "elementalsmithing:pure_crystal"},
  "fusing_craft_4": {"item": "elementalsmithing:pure_crystal"},
  "fusing_craft_5": {"item": "elementalsmithing:steel_ingot"},
  "fusing_craft_6": {"item": "minecraft:fire_charge"},
  "fusing_craft_7": {"item": "elementalsmithing:steel_ingot"},
  "fusing_left": {"item": "minecraft:magma_block"},
  "fusing_right": {"item": "minecraft:magma_block"},
  "result": {"item": "elementalsmithing:flame_core"}
}